antigcast/__init__.py
antigcast/__main__.py
antigcast/config.py
antigcast/pyromod/__init__.py
antigcast/pyromod/filters/__init__.py
antigcast/pyromod/filters/filters.py
antigcast/pyromod/helpers/__init__.py
antigcast/pyromod/helpers/helpers.py
antigcast/pyromod/listen/__init__.py
antigcast/pyromod/listen/listen.py
antigcast/pyromod/nav/__init__.py
antigcast/pyromod/nav/pagination.py
antigcast/pyromod/utils/__init__.py
antigcast/pyromod/utils/utils.py
anti_gikes-0.1.0.dist-info/LICENSE
anti_gikes-0.1.0.dist-info/METADATA
anti_gikes-0.1.0.dist-info/WHEEL
anti_gikes-0.1.0.dist-info/entry_points.txt
anti_gikes-0.1.0.dist-info/top_level.txt
anti_gikes-0.1.0.dist-info/RECORD
