Metadata-Version: 2.1
Name: anti-gikes
Version: 0.1.0
Summary: Deskripsi paket
Author-email: LaangYB <sedekgaming123@gmail.com>
License-File: LICENSE
